env_alias/__init__.py
env_alias/exceptions.py
env_alias/lib/__init__.py
env_alias/lib/definitions.py
env_alias/lib/generator.py
env_alias/lib/logger.py
env_alias/lib/selector.py
env_alias/lib/source.py
env_alias/main.py
env_alias/models/envalias_definition.py
env_alias/models/sourced_content.py
env_alias/py.typed
env_alias-0.5.3.dist-info/LICENSE
env_alias-0.5.3.dist-info/METADATA
env_alias-0.5.3.dist-info/WHEEL
env_alias-0.5.3.dist-info/entry_points.txt
env_alias-0.5.3.dist-info/RECORD
