Metadata-Version: 2.1
Name: env-alias
Version: 0.5.3
Summary: Powerful helper utility to create shell alias commands to easily set collections of environment variables often with secret values from a variety of data-sources and data-formats.
License: BSD-2-Clause
Keywords: env-alias,shell,env,alias,bash
Author: Nicholas de Jong
Author-email: contact@nicholasdejong.com
Requires-Python: >=3.8,<4.0
Classifier: Environment :: Console
Classifier: Intended Audience :: Developers
Classifier: Intended Audience :: Information Technology
Classifier: License :: OSI Approved :: BSD License
Classifier: Programming Language :: Python :: 3
Classifier: Programming Language :: Python :: 3.8
Classifier: Programming Language :: Python :: 3.9
Classifier: Programming Language :: Python :: 3.10
Classifier: Programming Language :: Python :: 3.11
Classifier: Programming Language :: Python :: 3.12
Requires-Dist: pyyaml (>=5.0)
Project-URL: Bug Tracker, https://github.com/ndejong/env-alias/issues
Project-URL: Documentation, https://env-alias.readthedocs.io/
Project-URL: Homepage, https://github.com/ndejong/env-alias
Project-URL: Repository, https://github.com/ndejong/env-alias
